{
  "group": "swordsandsandals",
  "type": "minecraft:crafting_shaped",
  "pattern": [
    "012",
    "345",
    " 7 "
  ],
  "key": {
    "0": {
      "item": "minecraft:log",
      "data": 32767
    },
    "1": {
      "item": "minecraft:log",
      "data": 32767
    },
    "2": {
      "item": "minecraft:log",
      "data": 32767
    },
    "3": {
      "item": "minecraft:log",
      "data": 32767
    },
    "4": {
      "item": "minecraft:iron_ingot"
    },
    "5": {
      "item": "minecraft:log",
      "data": 32767
    },
    "7": {
      "item": "minecraft:log",
      "data": 32767
    }
  },
  "result": {
    "item": "swordsandsandals:wooden_club",
    "count": 1
  }
}