{
  "_fv": 18,
  "_type": "recipe",
  "definition": {
    "recipeType": "Crafting",
    "xpReward": 0.0,
    "cookingTime": 200,
    "recipeRetstackSize": 6,
    "group": "",
    "recipeShapeless": false,
    "recipeSlots": [
      {
        "value": "CUSTOM:BlockOfCrystal"
      },
      {
        "value": "CUSTOM:BlockOfCrystal"
      },
      {
        "value": "CUSTOM:BlockOfCrystal"
      },
      {
        "value": "Blocks.GLOWSTONE"
      },
      {
        "value": "Blocks.GLOWSTONE"
      },
      {
        "value": "Blocks.GLOWSTONE"
      },
      {
        "value": "CUSTOM:BlockOfCrystal"
      },
      {
        "value": "CUSTOM:BlockOfCrystal"
      },
      {
        "value": "CUSTOM:BlockOfCrystal"
      }
    ],
    "recipeReturnStack": {
      "value": "CUSTOM:BlockOfPolishedCrystal"
    },
    "name": "bock_of_polishes_crystal_crafting",
    "namespace": "minecraft"
  }
}